{
  "title1": "It's time for another of",
  "title2": "Our <your family name>, Whole Family Movie Nights",
  "title3": "A <Your neighborhood or group name> tradition",
  "address": "<Your Street Address>",
  "food": "Pizza and snacks",
  "film": "Movies start",
  "rsvp": "Please RSVP with total number of guests. Recommended but optional: Bring your own folding/camping chair",
  "featuredFilms": "Featured Films…",
  "adults": "Adults (Cinema 1, Upstairs)",
  "kids": "Kids (Cinema 2, Downstairs)",
  "closing": "We hope to see you all there!",
  "helpYourself": "Help yourself to food and drink! Kids are downstairs with their own drinks and snacks.",
  "website": "https://your-website.com/invite"
}
